{"generated":"2026-06-29T22:59:53.868631","version":"etp2_1.0","run_number":26,"strategy":"COMPASS ETP2 — IWMO Timing (KAMA + XEON)","backtest_start":"2024-01-01","benchmark":"IWMO.MI","benchmark2":"VWCE.DE","segnali_oggi":{"s1":false,"s2":false,"s3":false,"n_segnali":0,"mom1m_iwmo":5.3,"kama_iwmo":104.3344,"kama_dir_iwmo":1,"price_iwmo":105.76,"descrizione":"S1✗ Mom1M=+5.3% | S2✗ Prezzo>KAMA(104.33) | S3✗ -2.8% da max60gg","quota_iwmo_pct":100,"quota_xeon_pct":0},"benchmark_perf":86.43,"benchmark2_perf":53.36,"outperformance":-19.27,"outperformance2":13.8,"batte_benchmark":false,"performance_totale_pct":67.16,"performance_totale_eur":67157.6,"capitale_attuale":167157.6,"max_drawdown":-8.91,"sharpe_6m":2.87,"sharpe_12m":1.81,"rolling_sharpe":[{"data":"2024-07-16","sharpe":4.935},{"data":"2024-07-30","sharpe":2.2},{"data":"2024-08-13","sharpe":1.439},{"data":"2024-08-27","sharpe":1.369},{"data":"2024-09-10","sharpe":0.293},{"data":"2024-09-24","sharpe":0.672},{"data":"2024-10-08","sharpe":1.036},{"data":"2024-10-22","sharpe":2.337},{"data":"2024-11-05","sharpe":1.154},{"data":"2024-11-19","sharpe":1.402},{"data":"2024-12-03","sharpe":1.998},{"data":"2024-12-17","sharpe":1.088},{"data":"2025-01-07","sharpe":1.128},{"data":"2025-01-21","sharpe":1.072},{"data":"2025-02-04","sharpe":3.415},{"data":"2025-02-18","sharpe":4.151},{"data":"2025-03-04","sharpe":1.292},{"data":"2025-03-18","sharpe":1.607},{"data":"2025-04-01","sharpe":0.899},{"data":"2025-04-15","sharpe":0.618},{"data":"2025-05-02","sharpe":0.452},{"data":"2025-05-16","sharpe":1.723},{"data":"2025-05-30","sharpe":0.924},{"data":"2025-06-13","sharpe":0.131},{"data":"2025-06-27","sharpe":0.287},{"data":"2025-07-11","sharpe":0.124},{"data":"2025-07-25","sharpe":0.069},{"data":"2025-08-08","sharpe":0.063},{"data":"2025-08-22","sharpe":-0.439},{"data":"2025-09-05","sharpe":1.396},{"data":"2025-09-19","sharpe":2.392},{"data":"2025-10-03","sharpe":2.757},{"data":"2025-10-17","sharpe":2.08},{"data":"2025-11-03","sharpe":1.781},{"data":"2025-11-17","sharpe":-0.479},{"data":"2025-12-01","sharpe":0.047},{"data":"2025-12-15","sharpe":0.634},{"data":"2026-01-05","sharpe":1.391},{"data":"2026-01-19","sharpe":2.273},{"data":"2026-02-02","sharpe":1.576},{"data":"2026-02-16","sharpe":0.173},{"data":"2026-03-02","sharpe":0.25},{"data":"2026-03-17","sharpe":-0.025},{"data":"2026-03-31","sharpe":-0.981},{"data":"2026-04-16","sharpe":-0.02},{"data":"2026-04-30","sharpe":1.245},{"data":"2026-05-15","sharpe":2.054},{"data":"2026-05-29","sharpe":3.259},{"data":"2026-06-12","sharpe":3.924},{"data":"2026-06-26","sharpe":4.448}],"drawdown_series":[{"data":"2024-01-25","dd":0.0},{"data":"2024-02-08","dd":0.0},{"data":"2024-02-22","dd":0.0},{"data":"2024-03-07","dd":0.0},{"data":"2024-03-21","dd":0.0},{"data":"2024-04-08","dd":-0.698},{"data":"2024-04-22","dd":-4.974},{"data":"2024-05-07","dd":-1.076},{"data":"2024-05-21","dd":0.0},{"data":"2024-06-04","dd":-0.694},{"data":"2024-06-18","dd":0.0},{"data":"2024-07-02","dd":-0.261},{"data":"2024-07-16","dd":0.0},{"data":"2024-07-30","dd":-6.532},{"data":"2024-08-13","dd":-6.82},{"data":"2024-08-27","dd":-4.884},{"data":"2024-09-10","dd":-7.744},{"data":"2024-09-24","dd":-3.426},{"data":"2024-10-08","dd":-1.817},{"data":"2024-10-22","dd":0.0},{"data":"2024-11-05","dd":-2.94},{"data":"2024-11-19","dd":0.0},{"data":"2024-12-03","dd":0.0},{"data":"2024-12-17","dd":-0.37},{"data":"2025-01-07","dd":-0.408},{"data":"2025-01-21","dd":0.0},{"data":"2025-02-04","dd":0.0},{"data":"2025-02-18","dd":0.0},{"data":"2025-03-04","dd":-7.618},{"data":"2025-03-18","dd":-8.915},{"data":"2025-04-01","dd":-8.804},{"data":"2025-04-15","dd":-8.73},{"data":"2025-05-02","dd":-6.821},{"data":"2025-05-16","dd":-3.15},{"data":"2025-05-30","dd":-4.207},{"data":"2025-06-13","dd":-5.214},{"data":"2025-06-27","dd":-4.811},{"data":"2025-07-11","dd":-5.638},{"data":"2025-07-25","dd":-4.675},{"data":"2025-08-08","dd":-2.918},{"data":"2025-08-22","dd":-2.549},{"data":"2025-09-05","dd":-3.974},{"data":"2025-09-19","dd":-2.869},{"data":"2025-10-03","dd":-1.754},{"data":"2025-10-17","dd":-3.157},{"data":"2025-11-03","dd":-2.176},{"data":"2025-11-17","dd":-4.324},{"data":"2025-12-01","dd":-4.189},{"data":"2025-12-15","dd":-3.955},{"data":"2026-01-05","dd":-1.521},{"data":"2026-01-19","dd":-0.257},{"data":"2026-02-02","dd":-0.918},{"data":"2026-02-16","dd":-2.599},{"data":"2026-03-02","dd":-2.032},{"data":"2026-03-17","dd":-4.163},{"data":"2026-03-31","dd":-5.55},{"data":"2026-04-16","dd":-2.011},{"data":"2026-04-30","dd":0.0},{"data":"2026-05-15","dd":0.0},{"data":"2026-05-29","dd":0.0},{"data":"2026-06-12","dd":0.0},{"data":"2026-06-26","dd":0.0}],"rend_per_anno":{"2024":{"01":6.31,"02":5.14,"03":6.18,"04":1.41,"05":-0.38,"06":0.93,"07":5.75,"08":-5.29,"09":-0.99,"10":6.42,"11":0.03,"12":6.61},"2025":{"01":-0.41,"02":3.2,"03":-5.0,"04":-1.28,"05":2.17,"06":1.72,"07":-0.45,"08":2.88,"09":-1.09,"10":2.31,"11":-0.43,"12":-2.06},"2026":{"01":2.79,"02":0.61,"03":-1.12,"04":0.02,"05":9.01,"06":6.04}},"rend_annuo":{"2024":36.19,"2025":1.24,"2026":18.23},"rend_iwmo_mese":{"2024":{"01":5.78,"02":8.78,"03":4.98,"04":-2.45,"05":2.3,"06":6.74,"07":-3.18,"08":-0.42,"09":1.46,"10":2.06,"11":6.96,"12":-0.8},"2025":{"01":5.46,"02":-1.94,"03":-9.07,"04":-1.5,"05":7.55,"06":0.27,"07":2.59,"08":-1.1,"09":4.2,"10":2.01,"11":-0.95,"12":1.25},"2026":{"01":1.41,"02":1.03,"03":-7.15,"04":15.7,"05":8.42,"06":6.08}},"rend_iwmo_anno":{"2024":36.3,"2025":8.04,"2026":26.59},"turnover_medio":0.0,"perf_per_step":{"0":{"media_sett":2.031,"n":41,"positivi":34,"label":"100% IWMO"},"2":{"media_sett":-2.553,"n":10,"positivi":1,"label":"30% IWMO"},"1":{"media_sett":-0.29,"n":9,"positivi":4,"label":"70% IWMO"},"3":{"media_sett":-0.641,"n":2,"positivi":1,"label":"100% XEON"}},"versioni":[{"data":"2024-01-11","n_segnali":0,"segnali":{"s1":false,"s2":false,"s3":false,"n_segnali":0,"descrizione":"Dati insufficienti"},"quota_iwmo":100.0,"quota_xeon":0.0,"composizione":[{"ticker":"IWMO.MI","nome":"iShares MSCI World Momentum","cat":"az_globale","sub":"GLOBAL_MOM","peso":100.0,"mom6m":null,"mom3m":null,"mom1m":null,"er":0.0,"kama":null,"kama_dir":0,"data_ingresso":"2024-01-01","azione":"MANTIENI","commento":"100% IWMO — nessun segnale attivo, massima esposizione momentum","importo":100000.0}],"capitale":100000.0},{"data":"2024-01-25","n_segnali":0,"segnali":{"s1":false,"s2":false,"s3":false,"n_segnali":0,"descrizione":"Dati insufficienti"},"quota_iwmo":100.0,"quota_xeon":0.0,"composizione":[{"ticker":"IWMO.MI","nome":"iShares MSCI World Momentum","cat":"az_globale","sub":"GLOBAL_MOM","peso":100.0,"mom6m":null,"mom3m":null,"mom1m":null,"er":0.0,"kama":null,"kama_dir":0,"data_ingresso":"2024-01-01","azione":"MANTIENI","commento":"100% IWMO — nessun segnale attivo, massima esposizione momentum","importo":106310.6}],"capitale":106310.6},{"data":"2024-02-08","n_segnali":0,"segnali":{"s1":false,"s2":false,"s3":false,"n_segnali":0,"descrizione":"Dati insufficienti"},"quota_iwmo":100.0,"quota_xeon":0.0,"composizione":[{"ticker":"IWMO.MI","nome":"iShares MSCI World Momentum","cat":"az_globale","sub":"GLOBAL_MOM","peso":100.0,"mom6m":null,"mom3m":null,"mom1m":null,"er":0.657,"kama":61.8616,"kama_dir":1,"data_ingresso":"2024-01-01","azione":"MANTIENI","commento":"100% IWMO — nessun segnale attivo, massima esposizione momentum","importo":111775.08}],"capitale":111775.08},{"data":"2024-02-22","n_segnali":0,"segnali":{"s1":false,"s2":false,"s3":false,"n_segnali":0,"descrizione":"Dati insufficienti"},"quota_iwmo":100.0,"quota_xeon":0.0,"composizione":[{"ticker":"IWMO.MI","nome":"iShares MSCI World Momentum","cat":"az_globale","sub":"GLOBAL_MOM","peso":100.0,"mom6m":null,"mom3m":null,"mom1m":8.6,"er":0.424,"kama":63.9423,"kama_dir":1,"data_ingresso":"2024-01-01","azione":"MANTIENI","commento":"100% IWMO — nessun segnale attivo, massima esposizione momentum","importo":114630.71}],"capitale":114630.71},{"data":"2024-03-07","n_segnali":0,"segnali":{"s1":false,"s2":false,"s3":false,"n_segnali":0,"descrizione":"Dati insufficienti"},"quota_iwmo":100.0,"quota_xeon":0.0,"composizione":[{"ticker":"IWMO.MI","nome":"iShares MSCI World Momentum","cat":"az_globale","sub":"GLOBAL_MOM","peso":100.0,"mom6m":null,"mom3m":null,"mom1m":6.6,"er":0.375,"kama":65.4495,"kama_dir":1,"data_ingresso":"2024-01-01","azione":"MANTIENI","commento":"100% IWMO — nessun segnale attivo, massima esposizione momentum","importo":118685.01}],"capitale":118685.01},{"data":"2024-03-21","n_segnali":0,"segnali":{"s1":false,"s2":false,"s3":false,"n_segnali":0,"descrizione":"Dati insufficienti"},"quota_iwmo":100.0,"quota_xeon":0.0,"composizione":[{"ticker":"IWMO.MI","nome":"iShares MSCI World Momentum","cat":"az_globale","sub":"GLOBAL_MOM","peso":100.0,"mom6m":null,"mom3m":null,"mom1m":9.26,"er":0.344,"kama":65.8746,"kama_dir":1,"data_ingresso":"2024-01-01","azione":"MANTIENI","commento":"100% IWMO — nessun segnale attivo, massima esposizione momentum","importo":121205.72}],"capitale":121205.72},{"data":"2024-04-08","n_segnali":0,"segnali":{"s1":false,"s2":false,"s3":false,"n_segnali":0,"descrizione":"Dati insufficienti"},"quota_iwmo":100.0,"quota_xeon":0.0,"composizione":[{"ticker":"IWMO.MI","nome":"iShares MSCI World Momentum","cat":"az_globale","sub":"GLOBAL_MOM","peso":100.0,"mom6m":null,"mom3m":null,"mom1m":2.4,"er":0.103,"kama":67.5171,"kama_dir":1,"data_ingresso":"2024-01-01","azione":"MANTIENI","commento":"100% IWMO — nessun segnale attivo, massima esposizione momentum","importo":120359.6}],"capitale":120359.6},{"data":"2024-04-22","n_segnali":0,"segnali":{"s1":false,"s2":false,"s3":false,"n_segnali":0,"descrizione":"Dati insufficienti"},"quota_iwmo":100.0,"quota_xeon":0.0,"composizione":[{"ticker":"IWMO.MI","nome":"iShares MSCI World Momentum","cat":"az_globale","sub":"GLOBAL_MOM","peso":100.0,"mom6m":null,"mom3m":10.22,"mom1m":-2.75,"er":0.38,"kama":67.0789,"kama_dir":-1,"data_ingresso":"2024-01-01","azione":"MANTIENI","commento":"100% IWMO — nessun segnale attivo, massima esposizione momentum","importo":115177.15}],"capitale":115177.15},{"data":"2024-05-07","n_segnali":0,"segnali":{"s1":false,"s2":false,"s3":false,"n_segnali":0,"descrizione":"Dati insufficienti"},"quota_iwmo":100.0,"quota_xeon":0.0,"composizione":[{"ticker":"IWMO.MI","nome":"iShares MSCI World Momentum","cat":"az_globale","sub":"GLOBAL_MOM","peso":100.0,"mom6m":null,"mom3m":8.92,"mom1m":-0.25,"er":0.02,"kama":66.9371,"kama_dir":1,"data_ingresso":"2024-01-01","azione":"MANTIENI","commento":"100% IWMO — nessun segnale attivo, massima esposizione momentum","importo":119901.28}],"capitale":119901.28},{"data":"2024-05-21","n_segnali":0,"segnali":{"s1":false,"s2":false,"s3":false,"n_segnali":0,"descrizione":"Dati insufficienti"},"quota_iwmo":100.0,"quota_xeon":0.0,"composizione":[{"ticker":"IWMO.MI","nome":"iShares MSCI World Momentum","cat":"az_globale","sub":"GLOBAL_MOM","peso":100.0,"mom6m":null,"mom3m":7.31,"mom1m":5.28,"er":0.399,"kama":68.2086,"kama_dir":1,"data_ingresso":"2024-01-01","azione":"MANTIENI","commento":"100% IWMO — nessun segnale attivo, massima esposizione momentum","importo":121857.92}],"capitale":121857.92},{"data":"2024-06-04","n_segnali":0,"segnali":{"s1":false,"s2":false,"s3":false,"n_segnali":0,"descrizione":"Dati insufficienti"},"quota_iwmo":100.0,"quota_xeon":0.0,"composizione":[{"ticker":"IWMO.MI","nome":"iShares MSCI World Momentum","cat":"az_globale","sub":"GLOBAL_MOM","peso":100.0,"mom6m":null,"mom3m":2.55,"mom1m":1.49,"er":0.1,"kama":69.475,"kama_dir":-1,"data_ingresso":"2024-01-01","azione":"MANTIENI","commento":"100% IWMO — nessun segnale attivo, massima esposizione momentum","importo":121011.81}],"capitale":121011.81},{"data":"2024-06-18","n_segnali":0,"segnali":{"s1":false,"s2":false,"s3":false,"n_segnali":0,"descrizione":"Dati insufficienti"},"quota_iwmo":100.0,"quota_xeon":0.0,"composizione":[{"ticker":"IWMO.MI","nome":"iShares MSCI World Momentum","cat":"az_globale","sub":"GLOBAL_MOM","peso":100.0,"mom6m":null,"mom3m":9.0,"mom1m":5.37,"er":0.433,"kama":71.5618,"kama_dir":1,"data_ingresso":"2024-01-01","azione":"MANTIENI","commento":"100% IWMO — nessun segnale attivo, massima esposizione momentum","importo":128309.53}],"capitale":128309.53},{"data":"2024-07-02","n_segnali":0,"segnali":{"s1":false,"s2":false,"s3":false,"n_segnali":0,"descrizione":"Dati insufficienti"},"quota_iwmo":100.0,"quota_xeon":0.0,"composizione":[{"ticker":"IWMO.MI","nome":"iShares MSCI World Momentum","cat":"az_globale","sub":"GLOBAL_MOM","peso":100.0,"mom6m":null,"mom3m":5.97,"mom1m":5.32,"er":0.461,"kama":72.4782,"kama_dir":1,"data_ingresso":"2024-01-01","azione":"MANTIENI","commento":"100% IWMO — nessun segnale attivo, massima esposizione momentum","importo":127974.61}],"capitale":127974.61},{"data":"2024-07-16","n_segnali":0,"segnali":{"s1":false,"s2":false,"s3":false,"n_segnali":0,"mom1m_iwmo":2.23,"kama_iwmo":73.2593,"kama_dir_iwmo":1,"price_iwmo":73.79,"descrizione":"S1✗ Mom1M=+2.2% | S2✗ Prezzo>KAMA(73.26) | S3✗ -0.6% da max60gg"},"quota_iwmo":100.0,"quota_xeon":0.0,"composizione":[{"ticker":"IWMO.MI","nome":"iShares MSCI World Momentum","cat":"az_globale","sub":"GLOBAL_MOM","peso":100.0,"mom6m":28.49,"mom3m":9.95,"mom1m":2.23,"er":0.151,"kama":73.2593,"kama_dir":1,"data_ingresso":"2024-01-01","azione":"MANTIENI","commento":"100% IWMO — nessun segnale attivo, massima esposizione momentum. IWMO mom1M=+2.2%, KAMA=73.26↑","importo":130072.27}],"capitale":130072.27},{"data":"2024-07-30","n_segnali":2,"segnali":{"s1":true,"s2":true,"s3":false,"n_segnali":2,"mom1m_iwmo":-4.78,"kama_iwmo":70.6156,"kama_dir_iwmo":-1,"price_iwmo":68.97,"descrizione":"S1✓ Mom1M=-4.8% | S2✓ Prezzo<KAMA(70.62) | S3✗ -7.1% da max60gg"},"quota_iwmo":30.0,"quota_xeon":70.0,"composizione":[{"ticker":"IWMO.MI","nome":"iShares MSCI World Momentum","cat":"az_globale","sub":"GLOBAL_MOM","peso":30.0,"mom6m":14.93,"mom3m":4.17,"mom1m":-4.78,"er":0.313,"kama":70.6156,"kama_dir":-1,"data_ingresso":"2024-01-01","azione":"RIDUCI","commento":"30% IWMO + 70% XEON — due segnali: trend KAMA invertito — ⚠️ aumentata protezione (da 0 a 2 segnali). IWMO mom1M=-4.8%, KAMA=70.62↓","importo":36472.76},{"ticker":"XEON.MI","nome":"Xtrackers EUR Overnight","cat":"monetario","sub":"CASH","peso":70.0,"mom6m":null,"mom3m":null,"mom1m":null,"er":1.0,"kama":null,"kama_dir":0,"data_ingresso":"2024-07-30","azione":"CASH","commento":"Protezione — 2 segnale/i attivi","importo":85103.12}],"capitale":121575.88},{"data":"2024-08-13","n_segnali":1,"segnali":{"s1":true,"s2":false,"s3":false,"n_segnali":1,"mom1m_iwmo":-7.65,"kama_iwmo":67.9839,"kama_dir_iwmo":1,"price_iwmo":68.05,"descrizione":"S1✓ Mom1M=-7.7% | S2✗ Prezzo>KAMA(67.98) | S3✗ -8.4% da max60gg"},"quota_iwmo":70.0,"quota_xeon":30.0,"composizione":[{"ticker":"IWMO.MI","nome":"iShares MSCI World Momentum","cat":"az_globale","sub":"GLOBAL_MOM","peso":70.0,"mom6m":6.38,"mom3m":-1.19,"mom1m":-7.65,"er":0.257,"kama":67.9839,"kama_dir":1,"data_ingresso":"2024-01-01","azione":"RIDUCI","commento":"70% IWMO + 30% XEON — primo segnale: momentum 1M negativo — ✅ ridotta protezione, rientro parziale (da 2 a 1 segnali). IWMO mom1M=-7.7%, KAMA=67.98↑","importo":84841.28},{"ticker":"XEON.MI","nome":"Xtrackers EUR Overnight","cat":"monetario","sub":"CASH","peso":30.0,"mom6m":null,"mom3m":null,"mom1m":null,"er":1.0,"kama":null,"kama_dir":0,"data_ingresso":"2024-08-13","azione":"CASH","commento":"Protezione — 1 segnale/i attivo","importo":36360.55}],"capitale":121201.83},{"data":"2024-08-27","n_segnali":1,"segnali":{"s1":false,"s2":true,"s3":false,"n_segnali":1,"mom1m_iwmo":1.45,"kama_iwmo":70.073,"kama_dir_iwmo":-1,"price_iwmo":70.03,"descrizione":"S1✗ Mom1M=+1.4% | S2✓ Prezzo<KAMA(70.07) | S3✗ -5.7% da max60gg"},"quota_iwmo":70.0,"quota_xeon":30.0,"composizione":[{"ticker":"IWMO.MI","nome":"iShares MSCI World Momentum","cat":"az_globale","sub":"GLOBAL_MOM","peso":70.0,"mom6m":7.72,"mom3m":-0.06,"mom1m":1.45,"er":0.053,"kama":70.073,"kama_dir":-1,"data_ingresso":"2024-01-01","azione":"RIDUCI","commento":"70% IWMO + 30% XEON — primo segnale: momentum 1M negativo. IWMO mom1M=+1.4%, KAMA=70.07↓","importo":86603.59},{"ticker":"XEON.MI","nome":"Xtrackers EUR Overnight","cat":"monetario","sub":"CASH","peso":30.0,"mom6m":null,"mom3m":null,"mom1m":null,"er":1.0,"kama":null,"kama_dir":0,"data_ingresso":"2024-08-27","azione":"CASH","commento":"Protezione — 1 segnale/i attivo","importo":37115.83}],"capitale":123719.42},{"data":"2024-09-10","n_segnali":1,"segnali":{"s1":false,"s2":true,"s3":false,"n_segnali":1,"mom1m_iwmo":0.34,"kama_iwmo":68.7741,"kama_dir_iwmo":-1,"price_iwmo":66.98,"descrizione":"S1✗ Mom1M=+0.3% | S2✓ Prezzo<KAMA(68.77) | S3✗ -9.8% da max60gg"},"quota_iwmo":70.0,"quota_xeon":30.0,"composizione":[{"ticker":"IWMO.MI","nome":"iShares MSCI World Momentum","cat":"az_globale","sub":"GLOBAL_MOM","peso":70.0,"mom6m":0.59,"mom3m":-6.32,"mom1m":0.34,"er":0.002,"kama":68.7741,"kama_dir":-1,"data_ingresso":"2024-01-01","azione":"RIDUCI","commento":"70% IWMO + 30% XEON — primo segnale: momentum 1M negativo. IWMO mom1M=+0.3%, KAMA=68.77↓","importo":83999.91},{"ticker":"XEON.MI","nome":"Xtrackers EUR Overnight","cat":"monetario","sub":"CASH","peso":30.0,"mom6m":null,"mom3m":null,"mom1m":null,"er":1.0,"kama":null,"kama_dir":0,"data_ingresso":"2024-09-10","azione":"CASH","commento":"Protezione — 1 segnale/i attivo","importo":35999.96}],"capitale":119999.87},{"data":"2024-09-24","n_segnali":0,"segnali":{"s1":false,"s2":false,"s3":false,"n_segnali":0,"mom1m_iwmo":2.13,"kama_iwmo":70.1452,"kama_dir_iwmo":1,"price_iwmo":71.42,"descrizione":"S1✗ Mom1M=+2.1% | S2✗ Prezzo>KAMA(70.15) | S3✗ -3.8% da max60gg"},"quota_iwmo":100.0,"quota_xeon":0.0,"composizione":[{"ticker":"IWMO.MI","nome":"iShares MSCI World Momentum","cat":"az_globale","sub":"GLOBAL_MOM","peso":100.0,"mom6m":3.7,"mom3m":-1.37,"mom1m":2.13,"er":0.095,"kama":70.1452,"kama_dir":1,"data_ingresso":"2024-01-01","azione":"MANTIENI","commento":"100% IWMO — nessun segnale attivo, massima esposizione momentum — ✅ ridotta protezione, rientro parziale (da 1 a 0 segnali). IWMO mom1M=+2.1%, KAMA=70.15↑","importo":125615.79}],"capitale":125615.79},{"data":"2024-10-08","n_segnali":0,"segnali":{"s1":false,"s2":false,"s3":false,"n_segnali":0,"mom1m_iwmo":8.67,"kama_iwmo":71.5489,"kama_dir_iwmo":1,"price_iwmo":72.61,"descrizione":"S1✗ Mom1M=+8.7% | S2✗ Prezzo>KAMA(71.55) | S3✗ -1.6% da max60gg"},"quota_iwmo":100.0,"quota_xeon":0.0,"composizione":[{"ticker":"IWMO.MI","nome":"iShares MSCI World Momentum","cat":"az_globale","sub":"GLOBAL_MOM","peso":100.0,"mom6m":5.92,"mom3m":-2.21,"mom1m":8.67,"er":0.605,"kama":71.5489,"kama_dir":1,"data_ingresso":"2024-01-01","azione":"MANTIENI","commento":"100% IWMO — nessun segnale attivo, massima esposizione momentum. IWMO mom1M=+8.7%, KAMA=71.55↑","importo":127708.8}],"capitale":127708.8},{"data":"2024-10-22","n_segnali":0,"segnali":{"s1":false,"s2":false,"s3":false,"n_segnali":0,"mom1m_iwmo":4.94,"kama_iwmo":74.6971,"kama_dir_iwmo":1,"price_iwmo":74.83,"descrizione":"S1✗ Mom1M=+4.9% | S2✗ Prezzo>KAMA(74.70) | S3✗ -0.6% da max60gg"},"quota_iwmo":100.0,"quota_xeon":0.0,"composizione":[{"ticker":"IWMO.MI","nome":"iShares MSCI World Momentum","cat":"az_globale","sub":"GLOBAL_MOM","peso":100.0,"mom6m":14.7,"mom3m":6.49,"mom1m":4.94,"er":0.569,"kama":74.6971,"kama_dir":1,"data_ingresso":"2024-01-01","azione":"MANTIENI","commento":"100% IWMO — nessun segnale attivo, massima esposizione momentum. IWMO mom1M=+4.9%, KAMA=74.70↑","importo":131613.41}],"capitale":131613.41},{"data":"2024-11-05","n_segnali":1,"segnali":{"s1":false,"s2":true,"s3":false,"n_segnali":1,"mom1m_iwmo":0.26,"kama_iwmo":73.1622,"kama_dir_iwmo":-1,"price_iwmo":72.63,"descrizione":"S1✗ Mom1M=+0.3% | S2✓ Prezzo<KAMA(73.16) | S3✗ -3.5% da max60gg"},"quota_iwmo":70.0,"quota_xeon":30.0,"composizione":[{"ticker":"IWMO.MI","nome":"iShares MSCI World Momentum","cat":"az_globale","sub":"GLOBAL_MOM","peso":70.0,"mom6m":6.65,"mom3m":10.53,"mom1m":0.26,"er":0.003,"kama":73.1622,"kama_dir":-1,"data_ingresso":"2024-01-01","azione":"RIDUCI","commento":"70% IWMO + 30% XEON — primo segnale: momentum 1M negativo — ⚠️ aumentata protezione (da 0 a 1 segnali). IWMO mom1M=+0.3%, KAMA=73.16↓","importo":89420.78},{"ticker":"XEON.MI","nome":"Xtrackers EUR Overnight","cat":"monetario","sub":"CASH","peso":30.0,"mom6m":null,"mom3m":null,"mom1m":null,"er":1.0,"kama":null,"kama_dir":0,"data_ingresso":"2024-11-05","azione":"CASH","commento":"Protezione — 1 segnale/i attivo","importo":38323.19}],"capitale":127743.97},{"data":"2024-11-19","n_segnali":0,"segnali":{"s1":false,"s2":false,"s3":false,"n_segnali":0,"mom1m_iwmo":1.75,"kama_iwmo":75.1593,"kama_dir_iwmo":1,"price_iwmo":76.06,"descrizione":"S1✗ Mom1M=+1.8% | S2✗ Prezzo>KAMA(75.16) | S3✗ -1.3% da max60gg"},"quota_iwmo":100.0,"quota_xeon":0.0,"composizione":[{"ticker":"IWMO.MI","nome":"iShares MSCI World Momentum","cat":"az_globale","sub":"GLOBAL_MOM","peso":100.0,"mom6m":8.94,"mom3m":7.92,"mom1m":1.75,"er":0.132,"kama":75.1593,"kama_dir":1,"data_ingresso":"2024-01-01","azione":"MANTIENI","commento":"100% IWMO — nessun segnale attivo, massima esposizione momentum — ✅ ridotta protezione, rientro parziale (da 1 a 0 segnali). IWMO mom1M=+1.8%, KAMA=75.16↑","importo":132020.05}],"capitale":132020.05},{"data":"2024-12-03","n_segnali":0,"segnali":{"s1":false,"s2":false,"s3":false,"n_segnali":0,"mom1m_iwmo":8.22,"kama_iwmo":76.6761,"kama_dir_iwmo":1,"price_iwmo":78.46,"descrizione":"S1✗ Mom1M=+8.2% | S2✗ Prezzo>KAMA(76.68) | S3✗ -0.0% da max60gg"},"quota_iwmo":100.0,"quota_xeon":0.0,"composizione":[{"ticker":"IWMO.MI","nome":"iShares MSCI World Momentum","cat":"az_globale","sub":"GLOBAL_MOM","peso":100.0,"mom6m":11.16,"mom3m":16.07,"mom1m":8.22,"er":0.514,"kama":76.6761,"kama_dir":1,"data_ingresso":"2024-01-01","azione":"MANTIENI","commento":"100% IWMO — nessun segnale attivo, massima esposizione momentum. IWMO mom1M=+8.2%, KAMA=76.68↑","importo":136185.82}],"capitale":136185.82},{"data":"2024-12-17","n_segnali":0,"segnali":{"s1":false,"s2":false,"s3":false,"n_segnali":0,"mom1m_iwmo":2.98,"kama_iwmo":77.3723,"kama_dir_iwmo":1,"price_iwmo":78.17,"descrizione":"S1✗ Mom1M=+3.0% | S2✗ Prezzo>KAMA(77.37) | S3✗ -0.9% da max60gg"},"quota_iwmo":100.0,"quota_xeon":0.0,"composizione":[{"ticker":"IWMO.MI","nome":"iShares MSCI World Momentum","cat":"az_globale","sub":"GLOBAL_MOM","peso":100.0,"mom6m":8.07,"mom3m":10.02,"mom1m":2.98,"er":0.251,"kama":77.3723,"kama_dir":1,"data_ingresso":"2024-01-01","azione":"MANTIENI","commento":"100% IWMO — nessun segnale attivo, massima esposizione momentum. IWMO mom1M=+3.0%, KAMA=77.37↑","importo":135682.46}],"capitale":135682.46},{"data":"2025-01-07","n_segnali":1,"segnali":{"s1":true,"s2":false,"s3":false,"n_segnali":1,"mom1m_iwmo":-0.41,"kama_iwmo":77.4065,"kama_dir_iwmo":1,"price_iwmo":78.14,"descrizione":"S1✓ Mom1M=-0.4% | S2✗ Prezzo>KAMA(77.41) | S3✗ -1.0% da max60gg"},"quota_iwmo":70.0,"quota_xeon":30.0,"composizione":[{"ticker":"IWMO.MI","nome":"iShares MSCI World Momentum","cat":"az_globale","sub":"GLOBAL_MOM","peso":70.0,"mom6m":6.57,"mom3m":8.86,"mom1m":-0.41,"er":0.04,"kama":77.4065,"kama_dir":1,"data_ingresso":"2024-01-01","azione":"RIDUCI","commento":"70% IWMO + 30% XEON — primo segnale: momentum 1M negativo — ⚠️ aumentata protezione (da 0 a 1 segnali). IWMO mom1M=-0.4%, KAMA=77.41↑","importo":94941.27},{"ticker":"XEON.MI","nome":"Xtrackers EUR Overnight","cat":"monetario","sub":"CASH","peso":30.0,"mom6m":null,"mom3m":null,"mom1m":null,"er":1.0,"kama":null,"kama_dir":0,"data_ingresso":"2025-01-07","azione":"CASH","commento":"Protezione — 1 segnale/i attivo","importo":40689.12}],"capitale":135630.39},{"data":"2025-01-21","n_segnali":0,"segnali":{"s1":false,"s2":false,"s3":false,"n_segnali":0,"mom1m_iwmo":1.17,"kama_iwmo":77.8588,"kama_dir_iwmo":1,"price_iwmo":79.56,"descrizione":"S1✗ Mom1M=+1.2% | S2✗ Prezzo>KAMA(77.86) | S3✗ -0.3% da max60gg"},"quota_iwmo":100.0,"quota_xeon":0.0,"composizione":[{"ticker":"IWMO.MI","nome":"iShares MSCI World Momentum","cat":"az_globale","sub":"GLOBAL_MOM","peso":100.0,"mom6m":12.69,"mom3m":5.71,"mom1m":1.17,"er":0.157,"kama":77.8588,"kama_dir":1,"data_ingresso":"2024-01-01","azione":"MANTIENI","commento":"100% IWMO — nessun segnale attivo, massima esposizione momentum — ✅ ridotta protezione, rientro parziale (da 1 a 0 segnali). IWMO mom1M=+1.2%, KAMA=77.86↑","importo":137396.81}],"capitale":137396.81},{"data":"2025-02-04","n_segnali":0,"segnali":{"s1":false,"s2":false,"s3":false,"n_segnali":0,"mom1m_iwmo":2.93,"kama_iwmo":79.0621,"kama_dir_iwmo":1,"price_iwmo":81.05,"descrizione":"S1✗ Mom1M=+2.9% | S2✗ Prezzo>KAMA(79.06) | S3✗ -0.6% da max60gg"},"quota_iwmo":100.0,"quota_xeon":0.0,"composizione":[{"ticker":"IWMO.MI","nome":"iShares MSCI World Momentum","cat":"az_globale","sub":"GLOBAL_MOM","peso":100.0,"mom6m":24.5,"mom3m":11.21,"mom1m":2.93,"er":0.233,"kama":79.0621,"kama_dir":1,"data_ingresso":"2024-01-01","azione":"MANTIENI","commento":"100% IWMO — nessun segnale attivo, massima esposizione momentum. IWMO mom1M=+2.9%, KAMA=79.06↑","importo":139969.99}],"capitale":139969.99},{"data":"2025-02-18","n_segnali":0,"segnali":{"s1":false,"s2":false,"s3":false,"n_segnali":0,"mom1m_iwmo":4.91,"kama_iwmo":82.259,"kama_dir_iwmo":1,"price_iwmo":83.35,"descrizione":"S1✗ Mom1M=+4.9% | S2✗ Prezzo>KAMA(82.26) | S3✗ -0.1% da max60gg"},"quota_iwmo":100.0,"quota_xeon":0.0,"composizione":[{"ticker":"IWMO.MI","nome":"iShares MSCI World Momentum","cat":"az_globale","sub":"GLOBAL_MOM","peso":100.0,"mom6m":18.8,"mom3m":8.64,"mom1m":4.91,"er":0.326,"kama":82.259,"kama_dir":1,"data_ingresso":"2024-01-01","azione":"MANTIENI","commento":"100% IWMO — nessun segnale attivo, massima esposizione momentum. IWMO mom1M=+4.9%, KAMA=82.26↑","importo":143941.99}],"capitale":143941.99},{"data":"2025-03-04","n_segnali":2,"segnali":{"s1":true,"s2":true,"s3":false,"n_segnali":2,"mom1m_iwmo":-4.8,"kama_iwmo":80.7681,"kama_dir_iwmo":-1,"price_iwmo":77.0,"descrizione":"S1✓ Mom1M=-4.8% | S2✓ Prezzo<KAMA(80.77) | S3✗ -7.9% da max60gg"},"quota_iwmo":30.0,"quota_xeon":70.0,"composizione":[{"ticker":"IWMO.MI","nome":"iShares MSCI World Momentum","cat":"az_globale","sub":"GLOBAL_MOM","peso":30.0,"mom6m":8.39,"mom3m":-0.81,"mom1m":-4.8,"er":0.267,"kama":80.7681,"kama_dir":-1,"data_ingresso":"2024-01-01","azione":"RIDUCI","commento":"30% IWMO + 70% XEON — due segnali: trend KAMA invertito — ⚠️ aumentata protezione (da 0 a 2 segnali). IWMO mom1M=-4.8%, KAMA=80.77↓","importo":39892.74},{"ticker":"XEON.MI","nome":"Xtrackers EUR Overnight","cat":"monetario","sub":"CASH","peso":70.0,"mom6m":null,"mom3m":null,"mom1m":null,"er":1.0,"kama":null,"kama_dir":0,"data_ingresso":"2025-03-04","azione":"CASH","commento":"Protezione — 2 segnale/i attivi","importo":93083.07}],"capitale":132975.81},{"data":"2025-03-18","n_segnali":3,"segnali":{"s1":true,"s2":true,"s3":true,"n_segnali":3,"mom1m_iwmo":-12.22,"kama_iwmo":74.0113,"kama_dir_iwmo":-1,"price_iwmo":73.21,"descrizione":"S1✓ Mom1M=-12.2% | S2✓ Prezzo<KAMA(74.01) | S3✓ -12.5% da max60gg"},"quota_iwmo":0.0,"quota_xeon":100.0,"composizione":[{"ticker":"XEON.MI","nome":"Xtrackers EUR Overnight","cat":"monetario","sub":"CASH","peso":100.0,"mom6m":null,"mom3m":null,"mom1m":null,"er":1.0,"kama":null,"kama_dir":0,"data_ingresso":"2025-03-18","azione":"CASH","commento":"Protezione — 3 segnale/i attivi","importo":131110.13}],"capitale":131110.13},{"data":"2025-04-01","n_segnali":3,"segnali":{"s1":true,"s2":true,"s3":true,"n_segnali":3,"mom1m_iwmo":-8.08,"kama_iwmo":74.5579,"kama_dir_iwmo":-1,"price_iwmo":73.82,"descrizione":"S1✓ Mom1M=-8.1% | S2✓ Prezzo<KAMA(74.56) | S3✓ -11.7% da max60gg"},"quota_iwmo":0.0,"quota_xeon":100.0,"composizione":[{"ticker":"XEON.MI","nome":"Xtrackers EUR Overnight","cat":"monetario","sub":"CASH","peso":100.0,"mom6m":null,"mom3m":null,"mom1m":null,"er":1.0,"kama":null,"kama_dir":0,"data_ingresso":"2025-04-01","azione":"CASH","commento":"Protezione — 3 segnale/i attivi","importo":131269.24}],"capitale":131269.24},{"data":"2025-04-15","n_segnali":2,"segnali":{"s1":true,"s2":false,"s3":true,"n_segnali":2,"mom1m_iwmo":-6.15,"kama_iwmo":68.645,"kama_dir_iwmo":1,"price_iwmo":69.13,"descrizione":"S1✓ Mom1M=-6.2% | S2✗ Prezzo>KAMA(68.64) | S3✓ -17.3% da max60gg"},"quota_iwmo":30.0,"quota_xeon":70.0,"composizione":[{"ticker":"IWMO.MI","nome":"iShares MSCI World Momentum","cat":"az_globale","sub":"GLOBAL_MOM","peso":30.0,"mom6m":-6.96,"mom3m":-12.66,"mom1m":-6.15,"er":0.136,"kama":68.645,"kama_dir":1,"data_ingresso":"2024-01-01","azione":"RIDUCI","commento":"30% IWMO + 70% XEON — due segnali: trend KAMA invertito — ✅ ridotta protezione, rientro parziale (da 3 a 2 segnali). IWMO mom1M=-6.2%, KAMA=68.64↑","importo":39412.55},{"ticker":"XEON.MI","nome":"Xtrackers EUR Overnight","cat":"monetario","sub":"CASH","peso":70.0,"mom6m":null,"mom3m":null,"mom1m":null,"er":1.0,"kama":null,"kama_dir":0,"data_ingresso":"2025-04-15","azione":"CASH","commento":"Protezione — 2 segnale/i attivi","importo":91962.63}],"capitale":131375.18},{"data":"2025-05-02","n_segnali":1,"segnali":{"s1":false,"s2":false,"s3":true,"n_segnali":1,"mom1m_iwmo":1.43,"kama_iwmo":70.4003,"kama_dir_iwmo":1,"price_iwmo":73.76,"descrizione":"S1✗ Mom1M=+1.4% | S2✗ Prezzo>KAMA(70.40) | S3✓ -11.8% da max60gg"},"quota_iwmo":70.0,"quota_xeon":30.0,"composizione":[{"ticker":"IWMO.MI","nome":"iShares MSCI World Momentum","cat":"az_globale","sub":"GLOBAL_MOM","peso":70.0,"mom6m":-0.78,"mom3m":-8.44,"mom1m":1.43,"er":0.002,"kama":70.4003,"kama_dir":1,"data_ingresso":"2024-01-01","azione":"RIDUCI","commento":"70% IWMO + 30% XEON — primo segnale: momentum 1M negativo — ✅ ridotta protezione, rientro parziale (da 2 a 1 segnali). IWMO mom1M=+1.4%, KAMA=70.40↑","importo":93886.07},{"ticker":"XEON.MI","nome":"Xtrackers EUR Overnight","cat":"monetario","sub":"CASH","peso":30.0,"mom6m":null,"mom3m":null,"mom1m":null,"er":1.0,"kama":null,"kama_dir":0,"data_ingresso":"2025-05-02","azione":"CASH","commento":"Protezione — 1 segnale/i attivo","importo":40236.89}],"capitale":134122.96},{"data":"2025-05-16","n_segnali":0,"segnali":{"s1":false,"s2":false,"s3":false,"n_segnali":0,"mom1m_iwmo":14.56,"kama_iwmo":76.3841,"kama_dir_iwmo":1,"price_iwmo":77.89,"descrizione":"S1✗ Mom1M=+14.6% | S2✗ Prezzo>KAMA(76.38) | S3✗ -6.9% da max60gg"},"quota_iwmo":100.0,"quota_xeon":0.0,"composizione":[{"ticker":"IWMO.MI","nome":"iShares MSCI World Momentum","cat":"az_globale","sub":"GLOBAL_MOM","peso":100.0,"mom6m":1.08,"mom3m":-6.02,"mom1m":14.56,"er":0.586,"kama":76.3841,"kama_dir":1,"data_ingresso":"2024-01-01","azione":"MANTIENI","commento":"100% IWMO — nessun segnale attivo, massima esposizione momentum — ✅ ridotta protezione, rientro parziale (da 1 a 0 segnali). IWMO mom1M=+14.6%, KAMA=76.38↑","importo":139407.65}],"capitale":139407.65},{"data":"2025-05-30","n_segnali":0,"segnali":{"s1":false,"s2":false,"s3":false,"n_segnali":0,"mom1m_iwmo":7.55,"kama_iwmo":76.7499,"kama_dir_iwmo":1,"price_iwmo":77.04,"descrizione":"S1✗ Mom1M=+7.5% | S2✗ Prezzo>KAMA(76.75) | S3✗ -1.1% da max60gg"},"quota_iwmo":100.0,"quota_xeon":0.0,"composizione":[{"ticker":"IWMO.MI","nome":"iShares MSCI World Momentum","cat":"az_globale","sub":"GLOBAL_MOM","peso":100.0,"mom6m":-0.67,"mom3m":-4.87,"mom1m":7.55,"er":0.301,"kama":76.7499,"kama_dir":1,"data_ingresso":"2024-01-01","azione":"MANTIENI","commento":"100% IWMO — nessun segnale attivo, massima esposizione momentum. IWMO mom1M=+7.5%, KAMA=76.75↑","importo":137886.32}],"capitale":137886.32},{"data":"2025-06-13","n_segnali":2,"segnali":{"s1":true,"s2":true,"s3":false,"n_segnali":2,"mom1m_iwmo":-1.47,"kama_iwmo":77.0853,"kama_dir_iwmo":-1,"price_iwmo":76.23,"descrizione":"S1✓ Mom1M=-1.5% | S2✓ Prezzo<KAMA(77.09) | S3✗ -2.1% da max60gg"},"quota_iwmo":30.0,"quota_xeon":70.0,"composizione":[{"ticker":"IWMO.MI","nome":"iShares MSCI World Momentum","cat":"az_globale","sub":"GLOBAL_MOM","peso":30.0,"mom6m":-2.23,"mom3m":5.61,"mom1m":-1.47,"er":0.219,"kama":77.0853,"kama_dir":-1,"data_ingresso":"2024-01-01","azione":"RIDUCI","commento":"30% IWMO + 70% XEON — due segnali: trend KAMA invertito — ⚠️ aumentata protezione (da 0 a 2 segnali). IWMO mom1M=-1.5%, KAMA=77.09↓","importo":40930.98},{"ticker":"XEON.MI","nome":"Xtrackers EUR Overnight","cat":"monetario","sub":"CASH","peso":70.0,"mom6m":null,"mom3m":null,"mom1m":null,"er":1.0,"kama":null,"kama_dir":0,"data_ingresso":"2025-06-13","azione":"CASH","commento":"Protezione — 2 segnale/i attivi","importo":95505.61}],"capitale":136436.59},{"data":"2025-06-27","n_segnali":0,"segnali":{"s1":false,"s2":false,"s3":false,"n_segnali":0,"mom1m_iwmo":0.47,"kama_iwmo":76.7035,"kama_dir_iwmo":1,"price_iwmo":77.17,"descrizione":"S1✗ Mom1M=+0.5% | S2✗ Prezzo>KAMA(76.70) | S3✗ -0.9% da max60gg"},"quota_iwmo":100.0,"quota_xeon":0.0,"composizione":[{"ticker":"IWMO.MI","nome":"iShares MSCI World Momentum","cat":"az_globale","sub":"GLOBAL_MOM","peso":100.0,"mom6m":-0.25,"mom3m":3.22,"mom1m":0.47,"er":0.021,"kama":76.7035,"kama_dir":1,"data_ingresso":"2024-01-01","azione":"MANTIENI","commento":"100% IWMO — nessun segnale attivo, massima esposizione momentum — ✅ ridotta protezione, rientro parziale (da 2 a 0 segnali). IWMO mom1M=+0.5%, KAMA=76.70↑","importo":137016.23}],"capitale":137016.23},{"data":"2025-07-11","n_segnali":1,"segnali":{"s1":false,"s2":true,"s3":false,"n_segnali":1,"mom1m_iwmo":0.17,"kama_iwmo":76.7245,"kama_dir_iwmo":-1,"price_iwmo":76.5,"descrizione":"S1✗ Mom1M=+0.2% | S2✓ Prezzo<KAMA(76.72) | S3✗ -1.8% da max60gg"},"quota_iwmo":70.0,"quota_xeon":30.0,"composizione":[{"ticker":"IWMO.MI","nome":"iShares MSCI World Momentum","cat":"az_globale","sub":"GLOBAL_MOM","peso":70.0,"mom6m":-0.97,"mom3m":14.18,"mom1m":0.17,"er":0.035,"kama":76.7245,"kama_dir":-1,"data_ingresso":"2024-01-01","azione":"RIDUCI","commento":"70% IWMO + 30% XEON — primo segnale: momentum 1M negativo — ⚠️ aumentata protezione (da 0 a 1 segnali). IWMO mom1M=+0.2%, KAMA=76.72↓","importo":95078.65},{"ticker":"XEON.MI","nome":"Xtrackers EUR Overnight","cat":"monetario","sub":"CASH","peso":30.0,"mom6m":null,"mom3m":null,"mom1m":null,"er":1.0,"kama":null,"kama_dir":0,"data_ingresso":"2025-07-11","azione":"CASH","commento":"Protezione — 1 segnale/i attivo","importo":40747.99}],"capitale":135826.64},{"data":"2025-07-25","n_segnali":0,"segnali":{"s1":false,"s2":false,"s3":false,"n_segnali":0,"mom1m_iwmo":1.08,"kama_iwmo":76.8796,"kama_dir_iwmo":1,"price_iwmo":77.59,"descrizione":"S1✗ Mom1M=+1.1% | S2✗ Prezzo>KAMA(76.88) | S3✗ -0.4% da max60gg"},"quota_iwmo":100.0,"quota_xeon":0.0,"composizione":[{"ticker":"IWMO.MI","nome":"iShares MSCI World Momentum","cat":"az_globale","sub":"GLOBAL_MOM","peso":100.0,"mom6m":-0.67,"mom3m":9.56,"mom1m":1.08,"er":0.048,"kama":76.8796,"kama_dir":1,"data_ingresso":"2024-01-01","azione":"MANTIENI","commento":"100% IWMO — nessun segnale attivo, massima esposizione momentum — ✅ ridotta protezione, rientro parziale (da 1 a 0 segnali). IWMO mom1M=+1.1%, KAMA=76.88↑","importo":137213.15}],"capitale":137213.15},{"data":"2025-08-08","n_segnali":0,"segnali":{"s1":false,"s2":false,"s3":false,"n_segnali":0,"mom1m_iwmo":2.58,"kama_iwmo":77.7826,"kama_dir_iwmo":1,"price_iwmo":79.02,"descrizione":"S1✗ Mom1M=+2.6% | S2✗ Prezzo>KAMA(77.78) | S3✗ -0.3% da max60gg"},"quota_iwmo":100.0,"quota_xeon":0.0,"composizione":[{"ticker":"IWMO.MI","nome":"iShares MSCI World Momentum","cat":"az_globale","sub":"GLOBAL_MOM","peso":100.0,"mom6m":-4.9,"mom3m":2.2,"mom1m":2.58,"er":0.277,"kama":77.7826,"kama_dir":1,"data_ingresso":"2024-01-01","azione":"MANTIENI","commento":"100% IWMO — nessun segnale attivo, massima esposizione momentum. IWMO mom1M=+2.6%, KAMA=77.78↑","importo":139742.02}],"capitale":139742.02},{"data":"2025-08-22","n_segnali":0,"segnali":{"s1":false,"s2":false,"s3":false,"n_segnali":0,"mom1m_iwmo":2.75,"kama_iwmo":78.2615,"kama_dir_iwmo":1,"price_iwmo":79.32,"descrizione":"S1✗ Mom1M=+2.8% | S2✗ Prezzo>KAMA(78.26) | S3✗ -0.3% da max60gg"},"quota_iwmo":100.0,"quota_xeon":0.0,"composizione":[{"ticker":"IWMO.MI","nome":"iShares MSCI World Momentum","cat":"az_globale","sub":"GLOBAL_MOM","peso":100.0,"mom6m":-3.5,"mom3m":3.78,"mom1m":2.75,"er":0.253,"kama":78.2615,"kama_dir":1,"data_ingresso":"2024-01-01","azione":"MANTIENI","commento":"100% IWMO — nessun segnale attivo, massima esposizione momentum. IWMO mom1M=+2.8%, KAMA=78.26↑","importo":140272.56}],"capitale":140272.56},{"data":"2025-09-05","n_segnali":2,"segnali":{"s1":true,"s2":true,"s3":false,"n_segnali":2,"mom1m_iwmo":-0.91,"kama_iwmo":78.3021,"kama_dir_iwmo":-1,"price_iwmo":78.16,"descrizione":"S1✓ Mom1M=-0.9% | S2✓ Prezzo<KAMA(78.30) | S3✗ -1.8% da max60gg"},"quota_iwmo":30.0,"quota_xeon":70.0,"composizione":[{"ticker":"IWMO.MI","nome":"iShares MSCI World Momentum","cat":"az_globale","sub":"GLOBAL_MOM","peso":30.0,"mom6m":6.09,"mom3m":1.1,"mom1m":-0.91,"er":0.109,"kama":78.3021,"kama_dir":-1,"data_ingresso":"2024-01-01","azione":"RIDUCI","commento":"30% IWMO + 70% XEON — due segnali: trend KAMA invertito — ⚠️ aumentata protezione (da 0 a 2 segnali). IWMO mom1M=-0.9%, KAMA=78.30↓","importo":41466.35},{"ticker":"XEON.MI","nome":"Xtrackers EUR Overnight","cat":"monetario","sub":"CASH","peso":70.0,"mom6m":null,"mom3m":null,"mom1m":null,"er":1.0,"kama":null,"kama_dir":0,"data_ingresso":"2025-09-05","azione":"CASH","commento":"Protezione — 2 segnale/i attivi","importo":96754.83}],"capitale":138221.18},{"data":"2025-09-19","n_segnali":0,"segnali":{"s1":false,"s2":false,"s3":false,"n_segnali":0,"mom1m_iwmo":2.14,"kama_iwmo":79.6827,"kama_dir_iwmo":1,"price_iwmo":81.02,"descrizione":"S1✗ Mom1M=+2.1% | S2✗ Prezzo>KAMA(79.68) | S3✗ -0.4% da max60gg"},"quota_iwmo":100.0,"quota_xeon":0.0,"composizione":[{"ticker":"IWMO.MI","nome":"iShares MSCI World Momentum","cat":"az_globale","sub":"GLOBAL_MOM","peso":100.0,"mom6m":8.99,"mom3m":6.42,"mom1m":2.14,"er":0.169,"kama":79.6827,"kama_dir":1,"data_ingresso":"2024-01-01","azione":"MANTIENI","commento":"100% IWMO — nessun segnale attivo, massima esposizione momentum — ✅ ridotta protezione, rientro parziale (da 2 a 0 segnali). IWMO mom1M=+2.1%, KAMA=79.68↑","importo":139812.14}],"capitale":139812.14},{"data":"2025-10-03","n_segnali":0,"segnali":{"s1":false,"s2":false,"s3":false,"n_segnali":0,"mom1m_iwmo":3.92,"kama_iwmo":81.117,"kama_dir_iwmo":1,"price_iwmo":81.95,"descrizione":"S1✗ Mom1M=+3.9% | S2✗ Prezzo>KAMA(81.12) | S3✗ -0.1% da max60gg"},"quota_iwmo":100.0,"quota_xeon":0.0,"composizione":[{"ticker":"IWMO.MI","nome":"iShares MSCI World Momentum","cat":"az_globale","sub":"GLOBAL_MOM","peso":100.0,"mom6m":23.68,"mom3m":6.33,"mom1m":3.92,"er":0.507,"kama":81.117,"kama_dir":1,"data_ingresso":"2024-01-01","azione":"MANTIENI","commento":"100% IWMO — nessun segnale attivo, massima esposizione momentum. IWMO mom1M=+3.9%, KAMA=81.12↑","importo":141416.99}],"capitale":141416.99},{"data":"2025-10-17","n_segnali":2,"segnali":{"s1":true,"s2":true,"s3":false,"n_segnali":2,"mom1m_iwmo":-0.12,"kama_iwmo":81.9232,"kama_dir_iwmo":-1,"price_iwmo":80.78,"descrizione":"S1✓ Mom1M=-0.1% | S2✓ Prezzo<KAMA(81.92) | S3✗ -2.6% da max60gg"},"quota_iwmo":30.0,"quota_xeon":70.0,"composizione":[{"ticker":"IWMO.MI","nome":"iShares MSCI World Momentum","cat":"az_globale","sub":"GLOBAL_MOM","peso":30.0,"mom6m":20.24,"mom3m":4.11,"mom1m":-0.12,"er":0.033,"kama":81.9232,"kama_dir":-1,"data_ingresso":"2024-01-01","azione":"RIDUCI","commento":"30% IWMO + 70% XEON — due segnali: trend KAMA invertito — ⚠️ aumentata protezione (da 0 a 2 segnali). IWMO mom1M=-0.1%, KAMA=81.92↓","importo":41819.39},{"ticker":"XEON.MI","nome":"Xtrackers EUR Overnight","cat":"monetario","sub":"CASH","peso":70.0,"mom6m":null,"mom3m":null,"mom1m":null,"er":1.0,"kama":null,"kama_dir":0,"data_ingresso":"2025-10-17","azione":"CASH","commento":"Protezione — 2 segnale/i attivi","importo":97578.59}],"capitale":139397.98},{"data":"2025-11-03","n_segnali":0,"segnali":{"s1":false,"s2":false,"s3":false,"n_segnali":0,"mom1m_iwmo":1.72,"kama_iwmo":82.1699,"kama_dir_iwmo":1,"price_iwmo":83.34,"descrizione":"S1✗ Mom1M=+1.7% | S2✗ Prezzo>KAMA(82.17) | S3✗ -0.1% da max60gg"},"quota_iwmo":100.0,"quota_xeon":0.0,"composizione":[{"ticker":"IWMO.MI","nome":"iShares MSCI World Momentum","cat":"az_globale","sub":"GLOBAL_MOM","peso":100.0,"mom6m":13.79,"mom3m":6.07,"mom1m":1.72,"er":0.131,"kama":82.1699,"kama_dir":1,"data_ingresso":"2024-01-01","azione":"MANTIENI","commento":"100% IWMO — nessun segnale attivo, massima esposizione momentum — ✅ ridotta protezione, rientro parziale (da 2 a 0 segnali). IWMO mom1M=+1.7%, KAMA=82.17↑","importo":140809.63}],"capitale":140809.63},{"data":"2025-11-17","n_segnali":2,"segnali":{"s1":true,"s2":true,"s3":false,"n_segnali":2,"mom1m_iwmo":-0.96,"kama_iwmo":82.1325,"kama_dir_iwmo":-1,"price_iwmo":81.51,"descrizione":"S1✓ Mom1M=-1.0% | S2✓ Prezzo<KAMA(82.13) | S3✗ -2.3% da max60gg"},"quota_iwmo":30.0,"quota_xeon":70.0,"composizione":[{"ticker":"IWMO.MI","nome":"iShares MSCI World Momentum","cat":"az_globale","sub":"GLOBAL_MOM","peso":30.0,"mom6m":5.82,"mom3m":3.09,"mom1m":-0.96,"er":0.058,"kama":82.1325,"kama_dir":-1,"data_ingresso":"2024-01-01","azione":"RIDUCI","commento":"30% IWMO + 70% XEON — due segnali: trend KAMA invertito — ⚠️ aumentata protezione (da 0 a 2 segnali). IWMO mom1M=-1.0%, KAMA=82.13↓","importo":41315.31},{"ticker":"XEON.MI","nome":"Xtrackers EUR Overnight","cat":"monetario","sub":"CASH","peso":70.0,"mom6m":null,"mom3m":null,"mom1m":null,"er":1.0,"kama":null,"kama_dir":0,"data_ingresso":"2025-11-17","azione":"CASH","commento":"Protezione — 2 segnale/i attivi","importo":96402.4}],"capitale":137717.71},{"data":"2025-12-01","n_segnali":1,"segnali":{"s1":true,"s2":false,"s3":false,"n_segnali":1,"mom1m_iwmo":-1.84,"kama_iwmo":81.6503,"kama_dir_iwmo":1,"price_iwmo":81.78,"descrizione":"S1✓ Mom1M=-1.8% | S2✗ Prezzo>KAMA(81.65) | S3✗ -2.0% da max60gg"},"quota_iwmo":70.0,"quota_xeon":30.0,"composizione":[{"ticker":"IWMO.MI","nome":"iShares MSCI World Momentum","cat":"az_globale","sub":"GLOBAL_MOM","peso":70.0,"mom6m":5.14,"mom3m":4.9,"mom1m":-1.84,"er":0.101,"kama":81.6503,"kama_dir":1,"data_ingresso":"2024-01-01","azione":"RIDUCI","commento":"70% IWMO + 30% XEON — primo segnale: momentum 1M negativo — ✅ ridotta protezione, rientro parziale (da 2 a 1 segnali). IWMO mom1M=-1.8%, KAMA=81.65↑","importo":96538.26},{"ticker":"XEON.MI","nome":"Xtrackers EUR Overnight","cat":"monetario","sub":"CASH","peso":30.0,"mom6m":null,"mom3m":null,"mom1m":null,"er":1.0,"kama":null,"kama_dir":0,"data_ingresso":"2025-12-01","azione":"CASH","commento":"Protezione — 1 segnale/i attivo","importo":41373.54}],"capitale":137911.8},{"data":"2025-12-15","n_segnali":1,"segnali":{"s1":false,"s2":true,"s3":false,"n_segnali":1,"mom1m_iwmo":0.35,"kama_iwmo":82.7648,"kama_dir_iwmo":-1,"price_iwmo":82.04,"descrizione":"S1✗ Mom1M=+0.3% | S2✓ Prezzo<KAMA(82.76) | S3✗ -2.3% da max60gg"},"quota_iwmo":70.0,"quota_xeon":30.0,"composizione":[{"ticker":"IWMO.MI","nome":"iShares MSCI World Momentum","cat":"az_globale","sub":"GLOBAL_MOM","peso":70.0,"mom6m":7.35,"mom3m":2.26,"mom1m":0.35,"er":0.042,"kama":82.7648,"kama_dir":-1,"data_ingresso":"2024-01-01","azione":"RIDUCI","commento":"70% IWMO + 30% XEON — primo segnale: momentum 1M negativo. IWMO mom1M=+0.3%, KAMA=82.76↓","importo":96774.43},{"ticker":"XEON.MI","nome":"Xtrackers EUR Overnight","cat":"monetario","sub":"CASH","peso":30.0,"mom6m":null,"mom3m":null,"mom1m":null,"er":1.0,"kama":null,"kama_dir":0,"data_ingresso":"2025-12-15","azione":"CASH","commento":"Protezione — 1 segnale/i attivo","importo":41474.75}],"capitale":138249.18},{"data":"2026-01-05","n_segnali":0,"segnali":{"s1":false,"s2":false,"s3":false,"n_segnali":0,"mom1m_iwmo":2.97,"kama_iwmo":82.8333,"kama_dir_iwmo":1,"price_iwmo":84.97,"descrizione":"S1✗ Mom1M=+3.0% | S2✗ Prezzo>KAMA(82.83) | S3✗ -0.0% da max60gg"},"quota_iwmo":100.0,"quota_xeon":0.0,"composizione":[{"ticker":"IWMO.MI","nome":"iShares MSCI World Momentum","cat":"az_globale","sub":"GLOBAL_MOM","peso":100.0,"mom6m":11.92,"mom3m":4.04,"mom1m":2.97,"er":0.263,"kama":82.8333,"kama_dir":1,"data_ingresso":"2024-01-01","azione":"MANTIENI","commento":"100% IWMO — nessun segnale attivo, massima esposizione momentum — ✅ ridotta protezione, rientro parziale (da 1 a 0 segnali). IWMO mom1M=+3.0%, KAMA=82.83↑","importo":141752.96}],"capitale":141752.96},{"data":"2026-01-19","n_segnali":0,"segnali":{"s1":false,"s2":false,"s3":false,"n_segnali":0,"mom1m_iwmo":5.14,"kama_iwmo":85.5607,"kama_dir_iwmo":1,"price_iwmo":86.06,"descrizione":"S1✗ Mom1M=+5.1% | S2✗ Prezzo>KAMA(85.56) | S3✗ -1.4% da max60gg"},"quota_iwmo":100.0,"quota_xeon":0.0,"composizione":[{"ticker":"IWMO.MI","nome":"iShares MSCI World Momentum","cat":"az_globale","sub":"GLOBAL_MOM","peso":100.0,"mom6m":12.13,"mom3m":4.7,"mom1m":5.14,"er":0.267,"kama":85.5607,"kama_dir":1,"data_ingresso":"2024-01-01","azione":"MANTIENI","commento":"100% IWMO — nessun segnale attivo, massima esposizione momentum. IWMO mom1M=+5.1%, KAMA=85.56↑","importo":143571.37}],"capitale":143571.37},{"data":"2026-02-02","n_segnali":0,"segnali":{"s1":false,"s2":false,"s3":false,"n_segnali":0,"mom1m_iwmo":2.51,"kama_iwmo":85.2068,"kama_dir_iwmo":1,"price_iwmo":85.49,"descrizione":"S1✗ Mom1M=+2.5% | S2✗ Prezzo>KAMA(85.21) | S3✗ -2.1% da max60gg"},"quota_iwmo":100.0,"quota_xeon":0.0,"composizione":[{"ticker":"IWMO.MI","nome":"iShares MSCI World Momentum","cat":"az_globale","sub":"GLOBAL_MOM","peso":100.0,"mom6m":8.24,"mom3m":2.72,"mom1m":2.51,"er":0.044,"kama":85.2068,"kama_dir":1,"data_ingresso":"2024-01-01","azione":"MANTIENI","commento":"100% IWMO — nessun segnale attivo, massima esposizione momentum. IWMO mom1M=+2.5%, KAMA=85.21↑","importo":142620.46}],"capitale":142620.46},{"data":"2026-02-16","n_segnali":2,"segnali":{"s1":true,"s2":true,"s3":false,"n_segnali":2,"mom1m_iwmo":-3.6,"kama_iwmo":84.7081,"kama_dir_iwmo":-1,"price_iwmo":84.04,"descrizione":"S1✓ Mom1M=-3.6% | S2✓ Prezzo<KAMA(84.71) | S3✗ -3.7% da max60gg"},"quota_iwmo":30.0,"quota_xeon":70.0,"composizione":[{"ticker":"IWMO.MI","nome":"iShares MSCI World Momentum","cat":"az_globale","sub":"GLOBAL_MOM","peso":30.0,"mom6m":6.34,"mom3m":0.84,"mom1m":-3.6,"er":0.156,"kama":84.7081,"kama_dir":-1,"data_ingresso":"2024-01-01","azione":"RIDUCI","commento":"30% IWMO + 70% XEON — due segnali: trend KAMA invertito — ⚠️ aumentata protezione (da 0 a 2 segnali). IWMO mom1M=-3.6%, KAMA=84.71↓","importo":42060.44},{"ticker":"XEON.MI","nome":"Xtrackers EUR Overnight","cat":"monetario","sub":"CASH","peso":70.0,"mom6m":null,"mom3m":null,"mom1m":null,"er":1.0,"kama":null,"kama_dir":0,"data_ingresso":"2026-02-16","azione":"CASH","commento":"Protezione — 2 segnale/i attivi","importo":98141.03}],"capitale":140201.47},{"data":"2026-03-02","n_segnali":0,"segnali":{"s1":false,"s2":false,"s3":false,"n_segnali":0,"mom1m_iwmo":0.96,"kama_iwmo":85.1931,"kama_dir_iwmo":1,"price_iwmo":85.54,"descrizione":"S1✗ Mom1M=+1.0% | S2✗ Prezzo>KAMA(85.19) | S3✗ -2.0% da max60gg"},"quota_iwmo":100.0,"quota_xeon":0.0,"composizione":[{"ticker":"IWMO.MI","nome":"iShares MSCI World Momentum","cat":"az_globale","sub":"GLOBAL_MOM","peso":100.0,"mom6m":8.13,"mom3m":4.18,"mom1m":0.96,"er":0.003,"kama":85.1931,"kama_dir":1,"data_ingresso":"2024-01-01","azione":"MANTIENI","commento":"100% IWMO — nessun segnale attivo, massima esposizione momentum — ✅ ridotta protezione, rientro parziale (da 2 a 0 segnali). IWMO mom1M=+1.0%, KAMA=85.19↑","importo":141016.46}],"capitale":141016.46},{"data":"2026-03-17","n_segnali":2,"segnali":{"s1":true,"s2":true,"s3":false,"n_segnali":2,"mom1m_iwmo":-0.44,"kama_iwmo":84.4212,"kama_dir_iwmo":-1,"price_iwmo":83.68,"descrizione":"S1✓ Mom1M=-0.4% | S2✓ Prezzo<KAMA(84.42) | S3✗ -4.1% da max60gg"},"quota_iwmo":30.0,"quota_xeon":70.0,"composizione":[{"ticker":"IWMO.MI","nome":"iShares MSCI World Momentum","cat":"az_globale","sub":"GLOBAL_MOM","peso":30.0,"mom6m":2.9,"mom3m":-0.17,"mom1m":-0.44,"er":0.02,"kama":84.4212,"kama_dir":-1,"data_ingresso":"2024-01-01","azione":"RIDUCI","commento":"30% IWMO + 70% XEON — due segnali: trend KAMA invertito — ⚠️ aumentata protezione (da 0 a 2 segnali). IWMO mom1M=-0.4%, KAMA=84.42↓","importo":41385.05},{"ticker":"XEON.MI","nome":"Xtrackers EUR Overnight","cat":"monetario","sub":"CASH","peso":70.0,"mom6m":null,"mom3m":null,"mom1m":null,"er":1.0,"kama":null,"kama_dir":0,"data_ingresso":"2026-03-17","azione":"CASH","commento":"Protezione — 2 segnale/i attivi","importo":96565.12}],"capitale":137950.17},{"data":"2026-03-31","n_segnali":2,"segnali":{"s1":true,"s2":true,"s3":false,"n_segnali":2,"mom1m_iwmo":-7.15,"kama_iwmo":82.5149,"kama_dir_iwmo":-1,"price_iwmo":79.48,"descrizione":"S1✓ Mom1M=-7.2% | S2✓ Prezzo<KAMA(82.51) | S3✗ -8.9% da max60gg"},"quota_iwmo":30.0,"quota_xeon":70.0,"composizione":[{"ticker":"IWMO.MI","nome":"iShares MSCI World Momentum","cat":"az_globale","sub":"GLOBAL_MOM","peso":30.0,"mom6m":-1.92,"mom3m":-4.48,"mom1m":-7.15,"er":0.299,"kama":82.5149,"kama_dir":-1,"data_ingresso":"2024-01-01","azione":"RIDUCI","commento":"30% IWMO + 70% XEON — due segnali: trend KAMA invertito. IWMO mom1M=-7.2%, KAMA=82.51↓","importo":40785.91},{"ticker":"XEON.MI","nome":"Xtrackers EUR Overnight","cat":"monetario","sub":"CASH","peso":70.0,"mom6m":null,"mom3m":null,"mom1m":null,"er":1.0,"kama":null,"kama_dir":0,"data_ingresso":"2026-03-31","azione":"CASH","commento":"Protezione — 2 segnale/i attivi","importo":95167.13}],"capitale":135953.04},{"data":"2026-04-16","n_segnali":0,"segnali":{"s1":false,"s2":false,"s3":false,"n_segnali":0,"mom1m_iwmo":6.95,"kama_iwmo":87.5156,"kama_dir_iwmo":1,"price_iwmo":89.24,"descrizione":"S1✗ Mom1M=+7.0% | S2✗ Prezzo>KAMA(87.52) | S3✗ -0.0% da max60gg"},"quota_iwmo":100.0,"quota_xeon":0.0,"composizione":[{"ticker":"IWMO.MI","nome":"iShares MSCI World Momentum","cat":"az_globale","sub":"GLOBAL_MOM","peso":100.0,"mom6m":7.58,"mom3m":4.2,"mom1m":6.95,"er":0.267,"kama":87.5156,"kama_dir":1,"data_ingresso":"2024-01-01","azione":"MANTIENI","commento":"100% IWMO — nessun segnale attivo, massima esposizione momentum — ✅ ridotta protezione, rientro parziale (da 2 a 0 segnali). IWMO mom1M=+7.0%, KAMA=87.52↑","importo":141047.12}],"capitale":141047.12},{"data":"2026-04-30","n_segnali":0,"segnali":{"s1":false,"s2":false,"s3":false,"n_segnali":0,"mom1m_iwmo":15.83,"kama_iwmo":90.065,"kama_dir_iwmo":1,"price_iwmo":91.96,"descrizione":"S1✗ Mom1M=+15.8% | S2✗ Prezzo>KAMA(90.06) | S3✗ -0.0% da max60gg"},"quota_iwmo":100.0,"quota_xeon":0.0,"composizione":[{"ticker":"IWMO.MI","nome":"iShares MSCI World Momentum","cat":"az_globale","sub":"GLOBAL_MOM","peso":100.0,"mom6m":12.52,"mom3m":7.35,"mom1m":15.83,"er":0.632,"kama":90.065,"kama_dir":1,"data_ingresso":"2024-01-01","azione":"MANTIENI","commento":"100% IWMO — nessun segnale attivo, massima esposizione momentum. IWMO mom1M=+15.8%, KAMA=90.06↑","importo":145346.18}],"capitale":145346.18},{"data":"2026-05-15","n_segnali":0,"segnali":{"s1":false,"s2":false,"s3":false,"n_segnali":0,"mom1m_iwmo":9.46,"kama_iwmo":95.7048,"kama_dir_iwmo":1,"price_iwmo":97.28,"descrizione":"S1✗ Mom1M=+9.5% | S2✗ Prezzo>KAMA(95.70) | S3✗ -1.7% da max60gg"},"quota_iwmo":100.0,"quota_xeon":0.0,"composizione":[{"ticker":"IWMO.MI","nome":"iShares MSCI World Momentum","cat":"az_globale","sub":"GLOBAL_MOM","peso":100.0,"mom6m":20.49,"mom3m":13.86,"mom1m":9.46,"er":0.379,"kama":95.7048,"kama_dir":1,"data_ingresso":"2024-01-01","azione":"MANTIENI","commento":"100% IWMO — nessun segnale attivo, massima esposizione momentum. IWMO mom1M=+9.5%, KAMA=95.70↑","importo":153754.64}],"capitale":153754.64},{"data":"2026-05-29","n_segnali":0,"segnali":{"s1":false,"s2":false,"s3":false,"n_segnali":0,"mom1m_iwmo":10.13,"kama_iwmo":96.7287,"kama_dir_iwmo":1,"price_iwmo":99.7,"descrizione":"S1✗ Mom1M=+10.1% | S2✗ Prezzo>KAMA(96.73) | S3✗ -0.9% da max60gg"},"quota_iwmo":100.0,"quota_xeon":0.0,"composizione":[{"ticker":"IWMO.MI","nome":"iShares MSCI World Momentum","cat":"az_globale","sub":"GLOBAL_MOM","peso":100.0,"mom6m":25.8,"mom3m":14.93,"mom1m":10.13,"er":0.336,"kama":96.7287,"kama_dir":1,"data_ingresso":"2024-01-01","azione":"MANTIENI","commento":"100% IWMO — nessun segnale attivo, massima esposizione momentum. IWMO mom1M=+10.1%, KAMA=96.73↑","importo":157579.54}],"capitale":157579.54},{"data":"2026-06-12","n_segnali":0,"segnali":{"s1":false,"s2":false,"s3":false,"n_segnali":0,"mom1m_iwmo":4.23,"kama_iwmo":100.0594,"kama_dir_iwmo":1,"price_iwmo":103.16,"descrizione":"S1✗ Mom1M=+4.2% | S2✗ Prezzo>KAMA(100.06) | S3✗ -0.1% da max60gg"},"quota_iwmo":100.0,"quota_xeon":0.0,"composizione":[{"ticker":"IWMO.MI","nome":"iShares MSCI World Momentum","cat":"az_globale","sub":"GLOBAL_MOM","peso":100.0,"mom6m":24.56,"mom3m":24.18,"mom1m":4.23,"er":0.245,"kama":100.0594,"kama_dir":1,"data_ingresso":"2024-01-01","azione":"MANTIENI","commento":"100% IWMO — nessun segnale attivo, massima esposizione momentum. IWMO mom1M=+4.2%, KAMA=100.06↑","importo":163048.21}],"capitale":163048.21},{"data":"2026-06-26","n_segnali":0,"segnali":{"s1":false,"s2":false,"s3":false,"n_segnali":0,"mom1m_iwmo":5.3,"kama_iwmo":104.3344,"kama_dir_iwmo":1,"price_iwmo":105.76,"descrizione":"S1✗ Mom1M=+5.3% | S2✗ Prezzo>KAMA(104.33) | S3✗ -2.8% da max60gg"},"quota_iwmo":100.0,"quota_xeon":0.0,"composizione":[{"ticker":"IWMO.MI","nome":"iShares MSCI World Momentum","cat":"az_globale","sub":"GLOBAL_MOM","peso":100.0,"mom6m":27.84,"mom3m":30.87,"mom1m":5.3,"er":0.218,"kama":104.3344,"kama_dir":1,"data_ingresso":"2024-01-01","azione":"MANTIENI","commento":"100% IWMO — nessun segnale attivo, massima esposizione momentum. IWMO mom1M=+5.3%, KAMA=104.33↑","importo":167157.6}],"capitale":167157.6}],"composizione_corrente":[{"ticker":"IWMO.MI","nome":"iShares MSCI World Momentum","cat":"az_globale","sub":"GLOBAL_MOM","peso":100.0,"mom6m":27.84,"mom3m":30.87,"mom1m":5.3,"er":0.218,"kama":104.3344,"kama_dir":1,"data_ingresso":"2024-01-01","azione":"MANTIENI","commento":"100% IWMO — nessun segnale attivo, massima esposizione momentum. IWMO mom1M=+5.3%, KAMA=104.33↑","importo":167157.6}],"rendimenti":{"2024-01-25":6.3106,"2024-02-08":5.1401,"2024-02-22":2.5548,"2024-03-07":3.5368,"2024-03-21":2.1239,"2024-04-08":-0.6981,"2024-04-22":-4.3058,"2024-05-07":4.1016,"2024-05-21":1.6319,"2024-06-04":-0.6943,"2024-06-18":6.0306,"2024-07-02":-0.261,"2024-07-16":1.6391,"2024-07-30":-6.532,"2024-08-13":-0.3077,"2024-08-27":2.0772,"2024-09-10":-3.0064,"2024-09-24":4.6799,"2024-10-08":1.6662,"2024-10-22":3.0574,"2024-11-05":-2.94,"2024-11-19":3.3474,"2024-12-03":3.1554,"2024-12-17":-0.3696,"2025-01-07":-0.0384,"2025-01-21":1.3024,"2025-02-04":1.8728,"2025-02-18":2.8377,"2025-03-04":-7.6185,"2025-03-18":-1.403,"2025-04-01":0.1214,"2025-04-15":0.0807,"2025-05-02":2.0916,"2025-05-16":3.9402,"2025-05-30":-1.0913,"2025-06-13":-1.0514,"2025-06-27":0.4248,"2025-07-11":-0.8682,"2025-07-25":1.0208,"2025-08-08":1.843,"2025-08-22":0.3797,"2025-09-05":-1.4624,"2025-09-19":1.151,"2025-10-03":1.1479,"2025-10-17":-1.4277,"2025-11-03":1.0127,"2025-11-17":-2.1958,"2025-12-01":0.1409,"2025-12-15":0.2446,"2026-01-05":2.5344,"2026-01-19":1.2828,"2026-02-02":-0.6623,"2026-02-16":-1.6961,"2026-03-02":0.5813,"2026-03-17":-2.1744,"2026-03-31":-1.4477,"2026-04-16":3.7469,"2026-04-30":3.048,"2026-05-15":5.7851,"2026-05-29":2.4877,"2026-06-12":3.4704,"2026-06-26":2.5204},"equity_mensile":[{"mese":"2024-01","valore":106310.6},{"mese":"2024-02","valore":111775.07},{"mese":"2024-03","valore":118684.96},{"mese":"2024-04","valore":120359.57},{"mese":"2024-05","valore":119901.24},{"mese":"2024-06","valore":121011.85},{"mese":"2024-07","valore":127974.7},{"mese":"2024-08","valore":121201.92},{"mese":"2024-09","valore":120000.03},{"mese":"2024-10","valore":127708.92},{"mese":"2024-11","valore":127744.05},{"mese":"2024-12","valore":136185.91},{"mese":"2025-01","valore":135630.47},{"mese":"2025-02","valore":139970.09},{"mese":"2025-03","valore":132975.8},{"mese":"2025-04","valore":131269.32},{"mese":"2025-05","valore":134123.09},{"mese":"2025-06","valore":136436.71},{"mese":"2025-07","valore":135826.71},{"mese":"2025-08","valore":139742.07},{"mese":"2025-09","valore":138221.32},{"mese":"2025-10","valore":141417.15},{"mese":"2025-11","valore":140809.82},{"mese":"2025-12","valore":137911.96},{"mese":"2026-01","valore":141753.08},{"mese":"2026-02","valore":142620.62},{"mese":"2026-03","valore":141016.62},{"mese":"2026-04","valore":141047.27},{"mese":"2026-05","valore":153754.82},{"mese":"2026-06","valore":163048.43}],"storia_segnali":[{"data":"2024-01-11","n_segnali":0,"s1":false,"s2":false,"s3":false,"descrizione":"Dati insufficienti"},{"data":"2024-01-25","n_segnali":0,"s1":false,"s2":false,"s3":false,"descrizione":"Dati insufficienti"},{"data":"2024-02-08","n_segnali":0,"s1":false,"s2":false,"s3":false,"descrizione":"Dati insufficienti"},{"data":"2024-02-22","n_segnali":0,"s1":false,"s2":false,"s3":false,"descrizione":"Dati insufficienti"},{"data":"2024-03-07","n_segnali":0,"s1":false,"s2":false,"s3":false,"descrizione":"Dati insufficienti"},{"data":"2024-03-21","n_segnali":0,"s1":false,"s2":false,"s3":false,"descrizione":"Dati insufficienti"},{"data":"2024-04-08","n_segnali":0,"s1":false,"s2":false,"s3":false,"descrizione":"Dati insufficienti"},{"data":"2024-04-22","n_segnali":0,"s1":false,"s2":false,"s3":false,"descrizione":"Dati insufficienti"},{"data":"2024-05-07","n_segnali":0,"s1":false,"s2":false,"s3":false,"descrizione":"Dati insufficienti"},{"data":"2024-05-21","n_segnali":0,"s1":false,"s2":false,"s3":false,"descrizione":"Dati insufficienti"},{"data":"2024-06-04","n_segnali":0,"s1":false,"s2":false,"s3":false,"descrizione":"Dati insufficienti"},{"data":"2024-06-18","n_segnali":0,"s1":false,"s2":false,"s3":false,"descrizione":"Dati insufficienti"},{"data":"2024-07-02","n_segnali":0,"s1":false,"s2":false,"s3":false,"descrizione":"Dati insufficienti"},{"data":"2024-07-16","n_segnali":0,"s1":false,"s2":false,"s3":false,"descrizione":"S1✗ Mom1M=+2.2% | S2✗ Prezzo>KAMA(73.26) | S3✗ -0.6% da max60gg"},{"data":"2024-07-30","n_segnali":2,"s1":true,"s2":true,"s3":false,"descrizione":"S1✓ Mom1M=-4.8% | S2✓ Prezzo<KAMA(70.62) | S3✗ -7.1% da max60gg"},{"data":"2024-08-13","n_segnali":1,"s1":true,"s2":false,"s3":false,"descrizione":"S1✓ Mom1M=-7.7% | S2✗ Prezzo>KAMA(67.98) | S3✗ -8.4% da max60gg"},{"data":"2024-08-27","n_segnali":1,"s1":false,"s2":true,"s3":false,"descrizione":"S1✗ Mom1M=+1.4% | S2✓ Prezzo<KAMA(70.07) | S3✗ -5.7% da max60gg"},{"data":"2024-09-10","n_segnali":1,"s1":false,"s2":true,"s3":false,"descrizione":"S1✗ Mom1M=+0.3% | S2✓ Prezzo<KAMA(68.77) | S3✗ -9.8% da max60gg"},{"data":"2024-09-24","n_segnali":0,"s1":false,"s2":false,"s3":false,"descrizione":"S1✗ Mom1M=+2.1% | S2✗ Prezzo>KAMA(70.15) | S3✗ -3.8% da max60gg"},{"data":"2024-10-08","n_segnali":0,"s1":false,"s2":false,"s3":false,"descrizione":"S1✗ Mom1M=+8.7% | S2✗ Prezzo>KAMA(71.55) | S3✗ -1.6% da max60gg"},{"data":"2024-10-22","n_segnali":0,"s1":false,"s2":false,"s3":false,"descrizione":"S1✗ Mom1M=+4.9% | S2✗ Prezzo>KAMA(74.70) | S3✗ -0.6% da max60gg"},{"data":"2024-11-05","n_segnali":1,"s1":false,"s2":true,"s3":false,"descrizione":"S1✗ Mom1M=+0.3% | S2✓ Prezzo<KAMA(73.16) | S3✗ -3.5% da max60gg"},{"data":"2024-11-19","n_segnali":0,"s1":false,"s2":false,"s3":false,"descrizione":"S1✗ Mom1M=+1.8% | S2✗ Prezzo>KAMA(75.16) | S3✗ -1.3% da max60gg"},{"data":"2024-12-03","n_segnali":0,"s1":false,"s2":false,"s3":false,"descrizione":"S1✗ Mom1M=+8.2% | S2✗ Prezzo>KAMA(76.68) | S3✗ -0.0% da max60gg"},{"data":"2024-12-17","n_segnali":0,"s1":false,"s2":false,"s3":false,"descrizione":"S1✗ Mom1M=+3.0% | S2✗ Prezzo>KAMA(77.37) | S3✗ -0.9% da max60gg"},{"data":"2025-01-07","n_segnali":1,"s1":true,"s2":false,"s3":false,"descrizione":"S1✓ Mom1M=-0.4% | S2✗ Prezzo>KAMA(77.41) | S3✗ -1.0% da max60gg"},{"data":"2025-01-21","n_segnali":0,"s1":false,"s2":false,"s3":false,"descrizione":"S1✗ Mom1M=+1.2% | S2✗ Prezzo>KAMA(77.86) | S3✗ -0.3% da max60gg"},{"data":"2025-02-04","n_segnali":0,"s1":false,"s2":false,"s3":false,"descrizione":"S1✗ Mom1M=+2.9% | S2✗ Prezzo>KAMA(79.06) | S3✗ -0.6% da max60gg"},{"data":"2025-02-18","n_segnali":0,"s1":false,"s2":false,"s3":false,"descrizione":"S1✗ Mom1M=+4.9% | S2✗ Prezzo>KAMA(82.26) | S3✗ -0.1% da max60gg"},{"data":"2025-03-04","n_segnali":2,"s1":true,"s2":true,"s3":false,"descrizione":"S1✓ Mom1M=-4.8% | S2✓ Prezzo<KAMA(80.77) | S3✗ -7.9% da max60gg"},{"data":"2025-03-18","n_segnali":3,"s1":true,"s2":true,"s3":true,"descrizione":"S1✓ Mom1M=-12.2% | S2✓ Prezzo<KAMA(74.01) | S3✓ -12.5% da max60gg"},{"data":"2025-04-01","n_segnali":3,"s1":true,"s2":true,"s3":true,"descrizione":"S1✓ Mom1M=-8.1% | S2✓ Prezzo<KAMA(74.56) | S3✓ -11.7% da max60gg"},{"data":"2025-04-15","n_segnali":2,"s1":true,"s2":false,"s3":true,"descrizione":"S1✓ Mom1M=-6.2% | S2✗ Prezzo>KAMA(68.64) | S3✓ -17.3% da max60gg"},{"data":"2025-05-02","n_segnali":1,"s1":false,"s2":false,"s3":true,"descrizione":"S1✗ Mom1M=+1.4% | S2✗ Prezzo>KAMA(70.40) | S3✓ -11.8% da max60gg"},{"data":"2025-05-16","n_segnali":0,"s1":false,"s2":false,"s3":false,"descrizione":"S1✗ Mom1M=+14.6% | S2✗ Prezzo>KAMA(76.38) | S3✗ -6.9% da max60gg"},{"data":"2025-05-30","n_segnali":0,"s1":false,"s2":false,"s3":false,"descrizione":"S1✗ Mom1M=+7.5% | S2✗ Prezzo>KAMA(76.75) | S3✗ -1.1% da max60gg"},{"data":"2025-06-13","n_segnali":2,"s1":true,"s2":true,"s3":false,"descrizione":"S1✓ Mom1M=-1.5% | S2✓ Prezzo<KAMA(77.09) | S3✗ -2.1% da max60gg"},{"data":"2025-06-27","n_segnali":0,"s1":false,"s2":false,"s3":false,"descrizione":"S1✗ Mom1M=+0.5% | S2✗ Prezzo>KAMA(76.70) | S3✗ -0.9% da max60gg"},{"data":"2025-07-11","n_segnali":1,"s1":false,"s2":true,"s3":false,"descrizione":"S1✗ Mom1M=+0.2% | S2✓ Prezzo<KAMA(76.72) | S3✗ -1.8% da max60gg"},{"data":"2025-07-25","n_segnali":0,"s1":false,"s2":false,"s3":false,"descrizione":"S1✗ Mom1M=+1.1% | S2✗ Prezzo>KAMA(76.88) | S3✗ -0.4% da max60gg"},{"data":"2025-08-08","n_segnali":0,"s1":false,"s2":false,"s3":false,"descrizione":"S1✗ Mom1M=+2.6% | S2✗ Prezzo>KAMA(77.78) | S3✗ -0.3% da max60gg"},{"data":"2025-08-22","n_segnali":0,"s1":false,"s2":false,"s3":false,"descrizione":"S1✗ Mom1M=+2.8% | S2✗ Prezzo>KAMA(78.26) | S3✗ -0.3% da max60gg"},{"data":"2025-09-05","n_segnali":2,"s1":true,"s2":true,"s3":false,"descrizione":"S1✓ Mom1M=-0.9% | S2✓ Prezzo<KAMA(78.30) | S3✗ -1.8% da max60gg"},{"data":"2025-09-19","n_segnali":0,"s1":false,"s2":false,"s3":false,"descrizione":"S1✗ Mom1M=+2.1% | S2✗ Prezzo>KAMA(79.68) | S3✗ -0.4% da max60gg"},{"data":"2025-10-03","n_segnali":0,"s1":false,"s2":false,"s3":false,"descrizione":"S1✗ Mom1M=+3.9% | S2✗ Prezzo>KAMA(81.12) | S3✗ -0.1% da max60gg"},{"data":"2025-10-17","n_segnali":2,"s1":true,"s2":true,"s3":false,"descrizione":"S1✓ Mom1M=-0.1% | S2✓ Prezzo<KAMA(81.92) | S3✗ -2.6% da max60gg"},{"data":"2025-11-03","n_segnali":0,"s1":false,"s2":false,"s3":false,"descrizione":"S1✗ Mom1M=+1.7% | S2✗ Prezzo>KAMA(82.17) | S3✗ -0.1% da max60gg"},{"data":"2025-11-17","n_segnali":2,"s1":true,"s2":true,"s3":false,"descrizione":"S1✓ Mom1M=-1.0% | S2✓ Prezzo<KAMA(82.13) | S3✗ -2.3% da max60gg"},{"data":"2025-12-01","n_segnali":1,"s1":true,"s2":false,"s3":false,"descrizione":"S1✓ Mom1M=-1.8% | S2✗ Prezzo>KAMA(81.65) | S3✗ -2.0% da max60gg"},{"data":"2025-12-15","n_segnali":1,"s1":false,"s2":true,"s3":false,"descrizione":"S1✗ Mom1M=+0.3% | S2✓ Prezzo<KAMA(82.76) | S3✗ -2.3% da max60gg"},{"data":"2026-01-05","n_segnali":0,"s1":false,"s2":false,"s3":false,"descrizione":"S1✗ Mom1M=+3.0% | S2✗ Prezzo>KAMA(82.83) | S3✗ -0.0% da max60gg"},{"data":"2026-01-19","n_segnali":0,"s1":false,"s2":false,"s3":false,"descrizione":"S1✗ Mom1M=+5.1% | S2✗ Prezzo>KAMA(85.56) | S3✗ -1.4% da max60gg"},{"data":"2026-02-02","n_segnali":0,"s1":false,"s2":false,"s3":false,"descrizione":"S1✗ Mom1M=+2.5% | S2✗ Prezzo>KAMA(85.21) | S3✗ -2.1% da max60gg"},{"data":"2026-02-16","n_segnali":2,"s1":true,"s2":true,"s3":false,"descrizione":"S1✓ Mom1M=-3.6% | S2✓ Prezzo<KAMA(84.71) | S3✗ -3.7% da max60gg"},{"data":"2026-03-02","n_segnali":0,"s1":false,"s2":false,"s3":false,"descrizione":"S1✗ Mom1M=+1.0% | S2✗ Prezzo>KAMA(85.19) | S3✗ -2.0% da max60gg"},{"data":"2026-03-17","n_segnali":2,"s1":true,"s2":true,"s3":false,"descrizione":"S1✓ Mom1M=-0.4% | S2✓ Prezzo<KAMA(84.42) | S3✗ -4.1% da max60gg"},{"data":"2026-03-31","n_segnali":2,"s1":true,"s2":true,"s3":false,"descrizione":"S1✓ Mom1M=-7.2% | S2✓ Prezzo<KAMA(82.51) | S3✗ -8.9% da max60gg"},{"data":"2026-04-16","n_segnali":0,"s1":false,"s2":false,"s3":false,"descrizione":"S1✗ Mom1M=+7.0% | S2✗ Prezzo>KAMA(87.52) | S3✗ -0.0% da max60gg"},{"data":"2026-04-30","n_segnali":0,"s1":false,"s2":false,"s3":false,"descrizione":"S1✗ Mom1M=+15.8% | S2✗ Prezzo>KAMA(90.06) | S3✗ -0.0% da max60gg"},{"data":"2026-05-15","n_segnali":0,"s1":false,"s2":false,"s3":false,"descrizione":"S1✗ Mom1M=+9.5% | S2✗ Prezzo>KAMA(95.70) | S3✗ -1.7% da max60gg"},{"data":"2026-05-29","n_segnali":0,"s1":false,"s2":false,"s3":false,"descrizione":"S1✗ Mom1M=+10.1% | S2✗ Prezzo>KAMA(96.73) | S3✗ -0.9% da max60gg"},{"data":"2026-06-12","n_segnali":0,"s1":false,"s2":false,"s3":false,"descrizione":"S1✗ Mom1M=+4.2% | S2✗ Prezzo>KAMA(100.06) | S3✗ -0.1% da max60gg"},{"data":"2026-06-26","n_segnali":0,"s1":false,"s2":false,"s3":false,"descrizione":"S1✗ Mom1M=+5.3% | S2✗ Prezzo>KAMA(104.33) | S3✗ -2.8% da max60gg"}],"n_rebalancing":63}